LICENCE.txt
MANIFEST.in
README.rst
setup.cfg
setup.py
dependency_comb/__init__.py
dependency_comb/analyzer.py
dependency_comb/exceptions.py
dependency_comb/package.py
dependency_comb/parser.py
dependency_comb.egg-info/PKG-INFO
dependency_comb.egg-info/SOURCES.txt
dependency_comb.egg-info/dependency_links.txt
dependency_comb.egg-info/entry_points.txt
dependency_comb.egg-info/requires.txt
dependency_comb.egg-info/top_level.txt
dependency_comb.egg-info/zip-safe
dependency_comb/cli/__init__.py
dependency_comb/cli/analyze.py
dependency_comb/cli/entrypoint.py
dependency_comb/cli/formatter.py
dependency_comb/cli/report.py
dependency_comb/cli/version.py
dependency_comb/formatting/__init__.py
dependency_comb/formatting/base.py
dependency_comb/formatting/csv.py
dependency_comb/formatting/json_format.py
dependency_comb/formatting/rich.py
dependency_comb/formatting/rst.py
dependency_comb/utils/__init__.py
dependency_comb/utils/dates.py
dependency_comb/utils/jsons.py
dependency_comb/utils/lists.py
dependency_comb/utils/logger.py