Metadata-Version: 2.1
Name: dependency-comb
Version: 0.4.0
Summary: A tool to analyze requirements with Pypi API
Home-page: https://github.com/sveetch/dependency-comb
Author: David Thenon
Author-email: sveetch@gmail.com
License: MIT
Project-URL: Source Code, https://github.com/sveetch/dependency-comb
Project-URL: Issue Tracker, https://github.com/sveetch/dependency-comb/issues
Project-URL: Changelog, https://dependency-comb.readthedocs.io/en/latest/history.html
Project-URL: Documentation, https://dependency-comb.readthedocs.io/
Keywords: Python
Classifier: Development Status :: 4 - Beta
Classifier: Intended Audience :: Developers
Classifier: License :: OSI Approved :: MIT License
Classifier: Natural Language :: English
Classifier: Programming Language :: Python :: 3
Classifier: Programming Language :: Python :: 3.8
Classifier: Programming Language :: Python :: 3.9
Classifier: Programming Language :: Python :: 3.10
License-File: LICENCE.txt
Requires-Dist: click>=8.0
Requires-Dist: colorlog>=6.8.2
Requires-Dist: requests>=2.32.3
Requires-Dist: humanize>=4.9.0
Requires-Dist: packaging>=24.0
Requires-Dist: tabulate>=0.9.0
Provides-Extra: rich
Requires-Dist: rich>=13.6.0; extra == "rich"
Provides-Extra: dev
Requires-Dist: pytest>=7.0; extra == "dev"
Requires-Dist: freezegun>=1.2.0; extra == "dev"
Provides-Extra: quality
Requires-Dist: flake8>=6.0.0; extra == "quality"
Requires-Dist: tox>=4.11.0; extra == "quality"
Provides-Extra: doc
Requires-Dist: sphinx>=8.0.2; extra == "doc"
Requires-Dist: furo>=2024.8.6; extra == "doc"
Requires-Dist: sphinx-copybutton>=0.5.2; extra == "doc"
Provides-Extra: doc-live
Requires-Dist: livereload>=2.6.0; extra == "doc-live"
Provides-Extra: release
Requires-Dist: twine>=5.0.0; extra == "release"
